[{"id": "75f1b952-1f03-4db2-acde-14cafd612884", "channel_id": 1560386984, "url": "https://abualiexpress.com/en/en28316/", "date": "2024-06-03 07:51", "message": "Mexico: Claudia Sheinbaum stands to be the first woman to be elected president of Mexico.\n\nSheinbaum, who won the elections in Mexico this morning with about 60% of the votes, is Jewish, born to parents from Lithuania and Bulgaria, a scientist, a climate expert and a member of the left political current in Mexico. She has good relations with the US and makes sure to keep the media quiet about her being Jewish.\nShe has spoken out against Israel in the war with Hamas.", "location": "Mexico", "classification": "antisemitism", "score": 0.5409940608889032, "event_breakdown": "Antisemitism in Mexico: After the Israeli-Palestinian war was launched on Monday, Israeli institutions have been the target of riots in Mexico and Peru. In Mexico City, hundreds of people demonstrated in front of the Israeli embassy,   shouting slogans of \u201cGet out of here Israel!\u201d and \u201cViva Palestine!\u201d In M\u00e9rida (in the state of Yucat\u00e1n) the protesters blocked the entrance to the Israeli consulate with tires and lit them. In Mexico, in response to the violence against Jews in Mexico, which culminated in the arson and robbery of a kosher supermarket, Jews from various settlements in the country published an open letter that they posted on Facebook on Monday night, saying that they are not against the Palestinians. \u201cWe want peace for our Palestinian neighbors, who coexist and trade with us,\u201d they stressed."}]